vaex/graphql/__init__.py
vaex/graphql/__main__.py
vaex/graphql/_version.py
vaex/graphql/tornado.py
vaex_graphql-0.2.0.dist-info/LICENSE.txt
vaex_graphql-0.2.0.dist-info/METADATA
vaex_graphql-0.2.0.dist-info/WHEEL
vaex_graphql-0.2.0.dist-info/entry_points.txt
vaex_graphql-0.2.0.dist-info/top_level.txt
vaex_graphql-0.2.0.dist-info/RECORD
