Metadata-Version: 2.1
Name: vaex-graphql
Version: 0.2.0
Summary: GraphQL support for accessing vaex DataFrame
Home-page: https://www.github.com/vaexio/vaex
Author: Maarten A. Breddels
Author-email: maartenbreddels@gmail.com
License: MIT
Platform: UNKNOWN
Requires-Dist: vaex-core (<5,>=4.0.0)
Requires-Dist: graphene (<3,>=2.1.8)
Requires-Dist: graphene-tornado (<3,>=2.5.1)
